tamilkavi/__init__.py
tamilkavi/tamilkavipy.py
tamilkavi/kavisrc/jothi.json
tamilkavi-0.5.0.dist-info/licenses/LICENSE
tamilkavi-0.5.0.dist-info/METADATA
tamilkavi-0.5.0.dist-info/WHEEL
tamilkavi-0.5.0.dist-info/entry_points.txt
tamilkavi-0.5.0.dist-info/top_level.txt
tamilkavi-0.5.0.dist-info/RECORD
