Metadata-Version: 2.4
Name: tamilkavi
Version: 0.5.0
Summary: A command-line tool for exploring Tamil Kavithaigal.
Home-page: https://github.com/anandsundaramoorthysa/tamilkavi
Author: ANAND SUNDARAMOORTHY SA and Boopalan S
Author-email: sanand03072005@gmail.com, content.boopalan@gmail.com
License: MIT
Keywords: tamil,kavi,poetry,tamil poetry,text processing
Classifier: Programming Language :: Python :: 3
Classifier: License :: OSI Approved :: MIT License
Classifier: Operating System :: OS Independent
Classifier: Development Status :: 5 - Production/Stable
Classifier: Environment :: Console
Classifier: Natural Language :: Tamil
Classifier: Topic :: Text Processing
Classifier: Programming Language :: Python :: 3.7
Classifier: Programming Language :: Python :: 3.8
Classifier: Programming Language :: Python :: 3.9
Classifier: Programming Language :: Python :: 3.10
Classifier: Programming Language :: Python :: 3.11
Classifier: Programming Language :: Python :: 3.12
Requires-Python: >=3.7
License-File: LICENSE
Requires-Dist: prettytable>=3.0.0
Requires-Dist: importlib_resources; python_version < "3.9"
Dynamic: author
Dynamic: author-email
Dynamic: classifier
Dynamic: description
Dynamic: description-content-type
Dynamic: home-page
Dynamic: keywords
Dynamic: license
Dynamic: license-file
Dynamic: requires-dist
Dynamic: requires-python
Dynamic: summary
